hisak/idtools/__init__.py
hisak/idtools/base32.py
hisak/idtools/base58.py
hisak/idtools/uuid58.py
hisak/idtools/uuid7.py
hisak/idtools/xid.py
hisak_idtools-0.2.0.dist-info/LICENSE
hisak_idtools-0.2.0.dist-info/METADATA
hisak_idtools-0.2.0.dist-info/WHEEL
hisak_idtools-0.2.0.dist-info/top_level.txt
hisak_idtools-0.2.0.dist-info/RECORD
